fake_gcp_manager_for_roy.py
fake_gcp_manager_for_roy-0.1.dist-info/METADATA
fake_gcp_manager_for_roy-0.1.dist-info/WHEEL
fake_gcp_manager_for_roy-0.1.dist-info/entry_points.txt
fake_gcp_manager_for_roy-0.1.dist-info/top_level.txt
fake_gcp_manager_for_roy-0.1.dist-info/RECORD
