Metadata-Version: 2.1
Name: fake-gcp-manager-for-roy
Version: 0.1
Summary: UNKNOWN
Home-page: UNKNOWN
License: UNKNOWN
Platform: UNKNOWN
Requires-Dist: argparse
